juditha/__init__.py
juditha/aggregator.py
juditha/cli.py
juditha/io.py
juditha/model.py
juditha/predict.py
juditha/settings.py
juditha/store.py
juditha/validate.py
juditha-4.2.2.dist-info/METADATA
juditha-4.2.2.dist-info/WHEEL
juditha-4.2.2.dist-info/entry_points.txt
juditha-4.2.2.dist-info/licenses/LICENSE
juditha-4.2.2.dist-info/licenses/NOTICE
juditha-4.2.2.dist-info/RECORD
