Metadata-Version: 2.4
Name: juditha
Version: 4.2.2
Summary: A super-fast canonical name lookup service
License: AGPLv3+
License-File: LICENSE
License-File: NOTICE
Author: Simon Wörpel
Author-email: simon.woerpel@pm.me
Requires-Python: >=3.11,<4
Classifier: Intended Audience :: Developers
Classifier: Operating System :: OS Independent
Classifier: Programming Language :: Python
Classifier: Programming Language :: Python :: 3.11
Classifier: Programming Language :: Python :: 3.12
Classifier: Programming Language :: Python :: 3.13
Requires-Dist: anystore (>=0.4.0,<0.5.0)
Requires-Dist: duckdb (>=1.4.1,<2.0.0)
Requires-Dist: fasttext-numpy2 (>=0.10.4,<0.11.0)
Requires-Dist: followthemoney (>=4.2.2,<5.0.0)
Requires-Dist: ftmq (>=4.2.5,<5.0.0)
Requires-Dist: jellyfish (>=1.2.0,<2.0.0)
Requires-Dist: pandas (>=2.3.3,<3.0.0)
Requires-Dist: tantivy (>=0.25.0,<0.26.0)
